[
    {
        "title": "Palantir Foundry & AIP Builder Foundations",
        "issuer": "Palantir",
        "issuedDate": "2025",
        "link": "https://verify.skilljar.com/c/n8v8i9dsc7h4",
        "iconName": "palantir"
    },
    {
        "title": "Certified Ethical Hacker (CEH)",
        "issuer": "EC-Council",
        "issuedDate": "2022",
        "link": "https://drive.google.com/file/d/1EPbeiUAc_tvSC6fFtFaMqqaObLr5ANPJ/view?usp=sharing",
        "iconName": "security"
    },
    {
        "title": "Google Analytics Certification",
        "issuer": "Google",
        "issuedDate": "2024",
        "link": "https://drive.google.com/file/d/1s17Q3gP1MAMuV2dMZ9Ejopa73LPL8T8I/view?usp=sharing",
        "iconName": "google"
    },
    {
        "title": "BCG Data Science Virtual Internship",
        "issuer": "Boston Consulting Group",
        "issuedDate": "2023",
        "link": "https://drive.google.com/file/d/10Q_dgm6spWy2SgXdfpFimvlpk1NhYdLh/view?usp=sharing",
        "iconName": "university"
    },
    {
        "title": "HighRadius Data Science Program",
        "issuer": "HighRadius",
        "issuedDate": "2022",
        "link": "https://drive.google.com/file/d/1Zmtc-9Krb6SJ3zf5jPo7F8e9uCsSeZRX/view?usp=sharing",
        "iconName": "university"
    },
    {
        "title": "ISRO Space Science Certificate",
        "issuer": "Indian Space Research Organisation",
        "issuedDate": "2021",
        "link": "https://drive.google.com/file/d/1eyW0d1jNBZ2MbtaI7PCxWRXZ7NgjVL3K/view?usp=sharing",
        "iconName": "university"
    },
    {
        "title": "Graph Neural Networks Research Publication",
        "issuer": "IEEE ICECONF'23",
        "issuedDate": "2023",
        "link": "https://drive.google.com/file/d/1EPDfks4eui5p7mPrn_TaRtdqVax8z_w-/view?usp=sharing",
        "iconName": "ieee"
    },
    {
        "title": "AI Research Publication Certificate",
        "issuer": "IEEE",
        "issuedDate": "2023",
        "link": "https://drive.google.com/file/d/1-n0ntWtKTgiCY7NdRfWV6uxRqHi_yeT7/view?usp=sharing",
        "iconName": "ieee"
    },
    {
        "title": "Python Programming",
        "issuer": "Udemy",
        "issuedDate": "2021",
        "link": "https://drive.google.com/file/d/1x8HhDaH4-J70-IneGt_9jL1uy1_6c8Z3/view?usp=sharing",
        "iconName": "udemy"
    },
    {
        "title": "C Programming Certificate",
        "issuer": "SRM Institute",
        "issuedDate": "2020",
        "link": "https://drive.google.com/file/d/1E4qZCjTVVoKLh_nV-SWc8lK74aQzWUZ2/view?usp=sharing",
        "iconName": "university"
    },
    {
        "title": "Data Workshop Certificate",
        "issuer": "SRM Institute",
        "issuedDate": "2021",
        "link": "https://drive.google.com/file/d/1zjLgF7QZ_7x3FEi9IzvkT798-1zH9MbZ/view?usp=sharing",
        "iconName": "university"
    },
    {
        "title": "Making Sense with Data Workshop",
        "issuer": "Workshop Series",
        "issuedDate": "2021",
        "link": "https://drive.google.com/file/d/1DZ1vUiMzhJBUNUXet8C3uM7GIvQ5RN6Z/view?usp=sharing",
        "iconName": "coursera"
    },
    {
        "title": "EasyTransfer Internship Certificate",
        "issuer": "Cashfree Payments",
        "issuedDate": "2024",
        "link": "https://drive.google.com/file/d/1osc3ticyjhZiXzb4WWcZlFzFiYrT43zK/view?usp=sharing",
        "iconName": "university"
    },
    {
        "title": "Workshop Course Certificate",
        "issuer": "Workshop Series",
        "issuedDate": "2021",
        "link": "https://drive.google.com/file/d/1KharPx8jRoDFJvPRq36hP5EP8dYXKm-U/view?usp=sharing",
        "iconName": "coursera"
    }
]